{
  "type": "File",
  "start": 0,
  "end": 66,
  "loc": {
    "start": {
      "line": 1,
      "column": 0
    },
    "end": {
      "line": 5,
      "column": 0
    }
  },
  "program": {
    "type": "Program",
    "start": 0,
    "end": 66,
    "loc": {
      "start": {
        "line": 1,
        "column": 0
      },
      "end": {
        "line": 5,
        "column": 0
      }
    },
    "sourceType": "module",
    "body": [
      {
        "type": "ImportDeclaration",
        "start": 0,
        "end": 32,
        "loc": {
          "start": {
            "line": 1,
            "column": 0
          },
          "end": {
            "line": 1,
            "column": 32
          }
        },
        "specifiers": [
          {
            "type": "ImportDefaultSpecifier",
            "start": 7,
            "end": 14,
            "loc": {
              "start": {
                "line": 1,
                "column": 7
              },
              "end": {
                "line": 1,
                "column": 14
              }
            },
            "local": {
              "type": "Identifier",
              "start": 7,
              "end": 14,
              "loc": {
                "start": {
                  "line": 1,
                  "column": 7
                },
                "end": {
                  "line": 1,
                  "column": 14
                },
                "identifierName": "addZero"
              },
              "name": "addZero"
            }
          }
        ],
        "source": {
          "type": "StringLiteral",
          "start": 20,
          "end": 31,
          "loc": {
            "start": {
              "line": 1,
              "column": 20
            },
            "end": {
              "line": 1,
              "column": 31
            }
          },
          "extra": {
            "rawValue": "./addZero",
            "raw": "'./addZero'"
          },
          "value": "./addZero"
        }
      },
      {
        "type": "ExportDefaultDeclaration",
        "start": 33,
        "end": 65,
        "loc": {
          "start": {
            "line": 2,
            "column": 0
          },
          "end": {
            "line": 4,
            "column": 2
          }
        },
        "declaration": {
          "type": "ObjectExpression",
          "start": 48,
          "end": 64,
          "loc": {
            "start": {
              "line": 2,
              "column": 15
            },
            "end": {
              "line": 4,
              "column": 1
            }
          },
          "properties": [
            {
              "type": "ObjectProperty",
              "start": 54,
              "end": 61,
              "loc": {
                "start": {
                  "line": 3,
                  "column": 4
                },
                "end": {
                  "line": 3,
                  "column": 11
                }
              },
              "method": false,
              "shorthand": true,
              "computed": false,
              "key": {
                "type": "Identifier",
                "start": 54,
                "end": 61,
                "loc": {
                  "start": {
                    "line": 3,
                    "column": 4
                  },
                  "end": {
                    "line": 3,
                    "column": 11
                  },
                  "identifierName": "addZero"
                },
                "name": "addZero"
              },
              "value": {
                "type": "Identifier",
                "start": 54,
                "end": 61,
                "loc": {
                  "start": {
                    "line": 3,
                    "column": 4
                  },
                  "end": {
                    "line": 3,
                    "column": 11
                  },
                  "identifierName": "addZero"
                },
                "name": "addZero"
              },
              "extra": {
                "shorthand": true
              }
            }
          ],
          "leadingComments": [],
          "trailingComments": []
        }
      }
    ],
    "directives": []
  },
  "comments": [],
  "tokens": [
    {
      "type": {
        "label": "import",
        "keyword": "import",
        "beforeExpr": false,
        "startsExpr": true,
        "rightAssociative": false,
        "isLoop": false,
        "isAssign": false,
        "prefix": false,
        "postfix": false,
        "binop": null,
        "updateContext": null
      },
      "value": "import",
      "start": 0,
      "end": 6,
      "loc": {
        "start": {
          "line": 1,
          "column": 0
        },
        "end": {
          "line": 1,
          "column": 6
        }
      }
    },
    {
      "type": {
        "label": "name",
        "beforeExpr": false,
        "startsExpr": true,
        "rightAssociative": false,
        "isLoop": false,
        "isAssign": false,
        "prefix": false,
        "postfix": false,
        "binop": null
      },
      "value": "addZero",
      "start": 7,
      "end": 14,
      "loc": {
        "start": {
          "line": 1,
          "column": 7
        },
        "end": {
          "line": 1,
          "column": 14
        }
      }
    },
    {
      "type": {
        "label": "name",
        "beforeExpr": false,
        "startsExpr": true,
        "rightAssociative": false,
        "isLoop": false,
        "isAssign": false,
        "prefix": false,
        "postfix": false,
        "binop": null
      },
      "value": "from",
      "start": 15,
      "end": 19,
      "loc": {
        "start": {
          "line": 1,
          "column": 15
        },
        "end": {
          "line": 1,
          "column": 19
        }
      }
    },
    {
      "type": {
        "label": "string",
        "beforeExpr": false,
        "startsExpr": true,
        "rightAssociative": false,
        "isLoop": false,
        "isAssign": false,
        "prefix": false,
        "postfix": false,
        "binop": null,
        "updateContext": null
      },
      "value": "./addZero",
      "start": 20,
      "end": 31,
      "loc": {
        "start": {
          "line": 1,
          "column": 20
        },
        "end": {
          "line": 1,
          "column": 31
        }
      }
    },
    {
      "type": {
        "label": ";",
        "beforeExpr": true,
        "startsExpr": false,
        "rightAssociative": false,
        "isLoop": false,
        "isAssign": false,
        "prefix": false,
        "postfix": false,
        "binop": null,
        "updateContext": null
      },
      "start": 31,
      "end": 32,
      "loc": {
        "start": {
          "line": 1,
          "column": 31
        },
        "end": {
          "line": 1,
          "column": 32
        }
      }
    },
    {
      "type": {
        "label": "export",
        "keyword": "export",
        "beforeExpr": false,
        "startsExpr": false,
        "rightAssociative": false,
        "isLoop": false,
        "isAssign": false,
        "prefix": false,
        "postfix": false,
        "binop": null,
        "updateContext": null
      },
      "value": "export",
      "start": 33,
      "end": 39,
      "loc": {
        "start": {
          "line": 2,
          "column": 0
        },
        "end": {
          "line": 2,
          "column": 6
        }
      }
    },
    {
      "type": {
        "label": "default",
        "keyword": "default",
        "beforeExpr": true,
        "startsExpr": false,
        "rightAssociative": false,
        "isLoop": false,
        "isAssign": false,
        "prefix": false,
        "postfix": false,
        "binop": null,
        "updateContext": null
      },
      "value": "default",
      "start": 40,
      "end": 47,
      "loc": {
        "start": {
          "line": 2,
          "column": 7
        },
        "end": {
          "line": 2,
          "column": 14
        }
      }
    },
    {
      "type": {
        "label": "{",
        "beforeExpr": true,
        "startsExpr": true,
        "rightAssociative": false,
        "isLoop": false,
        "isAssign": false,
        "prefix": false,
        "postfix": false,
        "binop": null
      },
      "start": 48,
      "end": 49,
      "loc": {
        "start": {
          "line": 2,
          "column": 15
        },
        "end": {
          "line": 2,
          "column": 16
        }
      }
    },
    {
      "type": {
        "label": "name",
        "beforeExpr": false,
        "startsExpr": true,
        "rightAssociative": false,
        "isLoop": false,
        "isAssign": false,
        "prefix": false,
        "postfix": false,
        "binop": null
      },
      "value": "addZero",
      "start": 54,
      "end": 61,
      "loc": {
        "start": {
          "line": 3,
          "column": 4
        },
        "end": {
          "line": 3,
          "column": 11
        }
      }
    },
    {
      "type": {
        "label": ",",
        "beforeExpr": true,
        "startsExpr": false,
        "rightAssociative": false,
        "isLoop": false,
        "isAssign": false,
        "prefix": false,
        "postfix": false,
        "binop": null,
        "updateContext": null
      },
      "start": 61,
      "end": 62,
      "loc": {
        "start": {
          "line": 3,
          "column": 11
        },
        "end": {
          "line": 3,
          "column": 12
        }
      }
    },
    {
      "type": {
        "label": "}",
        "beforeExpr": false,
        "startsExpr": false,
        "rightAssociative": false,
        "isLoop": false,
        "isAssign": false,
        "prefix": false,
        "postfix": false,
        "binop": null
      },
      "start": 63,
      "end": 64,
      "loc": {
        "start": {
          "line": 4,
          "column": 0
        },
        "end": {
          "line": 4,
          "column": 1
        }
      }
    },
    {
      "type": {
        "label": ";",
        "beforeExpr": true,
        "startsExpr": false,
        "rightAssociative": false,
        "isLoop": false,
        "isAssign": false,
        "prefix": false,
        "postfix": false,
        "binop": null,
        "updateContext": null
      },
      "start": 64,
      "end": 65,
      "loc": {
        "start": {
          "line": 4,
          "column": 1
        },
        "end": {
          "line": 4,
          "column": 2
        }
      }
    },
    {
      "type": {
        "label": "eof",
        "beforeExpr": false,
        "startsExpr": false,
        "rightAssociative": false,
        "isLoop": false,
        "isAssign": false,
        "prefix": false,
        "postfix": false,
        "binop": null,
        "updateContext": null
      },
      "start": 66,
      "end": 66,
      "loc": {
        "start": {
          "line": 5,
          "column": 0
        },
        "end": {
          "line": 5,
          "column": 0
        }
      }
    }
  ]
}